with_op/__init__.py
with_op/with_op.py
with_op-1.1.1.data/scripts/with-op
with_op-1.1.1.dist-info/AUTHORS.rst
with_op-1.1.1.dist-info/LICENSE
with_op-1.1.1.dist-info/METADATA
with_op-1.1.1.dist-info/WHEEL
with_op-1.1.1.dist-info/top_level.txt
with_op-1.1.1.dist-info/RECORD
