Metadata-Version: 2.1
Name: with-op
Version: 1.1.1
Summary: Script to stash 1Password command-line tool credentials into local keychain
Home-page: https://github.com/apiology/with_op
Author: Vince Broz
Author-email: vince@broz.cc
License: MIT license
Keywords: with_op
Platform: UNKNOWN
Classifier: Development Status :: 2 - Pre-Alpha
Classifier: Intended Audience :: Developers
Classifier: License :: OSI Approved :: MIT License
Classifier: Natural Language :: English
Classifier: Programming Language :: Python :: 3
Classifier: Programming Language :: Python :: 3.6
Classifier: Programming Language :: Python :: 3.7
Classifier: Programming Language :: Python :: 3.8
Classifier: Programming Language :: Python :: 3.9
Requires-Python: >=3.6
Requires-Dist: local-keychain-utils
Requires-Dist: prompt-for-password
